epl/geometry/__init__.py
epl/geometry/base.py
epl/geometry/collection.py
epl/geometry/geo.py
epl/geometry/linestring.py
epl/geometry/multilinestring.py
epl/geometry/multipoint.py
epl/geometry/multipolygon.py
epl/geometry/point.py
epl/geometry/polygon.py
epl/grpc/__init__.py
epl/grpc/geometry_service_pb2_grpc.py
epl/protobuf/__init__.py
epl/protobuf/geometry_pb2.py
epl.geometry-0.2.0.dist-info/LICENSE
epl.geometry-0.2.0.dist-info/METADATA
epl.geometry-0.2.0.dist-info/WHEEL
epl.geometry-0.2.0.dist-info/top_level.txt
epl.geometry-0.2.0.dist-info/RECORD
