Metadata-Version: 2.1
Name: epl.geometry
Version: 0.2.0
Summary: geometry library that extends shapely to work with Echo Park Labs gRPC geometry library
Home-page: https://github.com/geo-grpc/geometry-client-python
Author: David Raleigh
Author-email: davidraleigh@geometry.com
License: Apache 2.0
Platform: UNKNOWN
Classifier: Programming Language :: Python
Classifier: Programming Language :: Python :: 3
Classifier: Programming Language :: Python :: 3.5
Classifier: Programming Language :: Python :: 3.6
Requires-Python: >3.5.2
Requires-Dist: grpcio-tools
Requires-Dist: protobuf
Requires-Dist: shapely
